ltctplugin/esphomeota/__init__.py
ltctplugin/esphomeota/esphome.py
ltctplugin/esphomeota/gui.py
ltctplugin/esphomeota/uploader.wxui
ltctplugin/esphomeota/uploader.xrc
ltctplugin/esphomeota/work.py
ltchiptool_esphome_ota-1.4.0.dist-info/METADATA
ltchiptool_esphome_ota-1.4.0.dist-info/WHEEL
ltchiptool_esphome_ota-1.4.0.dist-info/RECORD
